.clang-format
.gitattributes
.gitignore
.pre-commit-config.yaml
CMakeLists.txt
CMakePresets.json
CODE_OF_CONDUCT.md
CONTRIBUTING.md
LICENSE
MANIFEST.in
Makefile
NOTICES
README.md
SECURITY.md
logo.svg
past_commits.txt
pyproject.toml
schema.json
setup.py
.github/PULL_REQUEST_TEMPLATE.md
.github/labeler.yml
.github/ISSUE_TEMPLATE/bug.md
.github/ISSUE_TEMPLATE/enhancement.md
.github/workflows/clang-format.yml
.github/workflows/cppcheck.yml
.github/workflows/fuzz.yml
.github/workflows/labeler.yml
.github/workflows/publish-pysear.yml
.github/workflows/ruff.yml
.github/workflows/test.yml
.vscode/c_cpp_properties.json
.vscode/extensions.json
.vscode/launch.json
.vscode/settings.json
cmake/clang.cmake
cmake/ibm-clang.cmake
debug/debug.c
dev_tools/README.md
dev_tools/convert_dirs.py
dev_tools/generate_doc_tables.py
dev_tools/load_seg_data.py
dev_tools/map_fields.py
externals/iconv/iconv.h
externals/json-schema-validator/LICENSE
externals/json-schema-validator/json-patch.cpp
externals/json-schema-validator/json-patch.hpp
externals/json-schema-validator/json-schema-draft7.json.cpp
externals/json-schema-validator/json-uri.cpp
externals/json-schema-validator/json-validator.cpp
externals/json-schema-validator/smtp-address-validator.cpp
externals/json-schema-validator/smtp-address-validator.hpp
externals/json-schema-validator/string-format-check.cpp
externals/json-schema-validator/nlohmann/json-schema.hpp
externals/json/nlohmann/LICENSE.MIT
externals/json/nlohmann/json.hpp
python/pysear.egg-info/PKG-INFO
python/pysear.egg-info/SOURCES.txt
python/pysear.egg-info/dependency_links.txt
python/pysear.egg-info/requires.txt
python/pysear.egg-info/top_level.txt
python/sear/_C.pyi
python/sear/__init__.py
python/sear/sear.py
python_tests/conftest.py
python_tests/helper.py
python_tests/test_connect.py
python_tests/test_dataset.py
python_tests/test_group.py
python_tests/test_keyring.py
python_tests/test_permit.py
python_tests/test_resource.py
python_tests/test_rrsf.py
python_tests/test_search.py
python_tests/test_setropts.py
python_tests/test_user.py
sear/conversion.cpp
sear/conversion.hpp
sear/extractor.hpp
sear/logger.cpp
sear/logger.hpp
sear/sear.cpp
sear/sear.h
