Metadata-Version: 2.4
Name: pysear
Version: 0.5.0
Summary: A unified and standardized interface to RACF callable services.
Author-email: Bobby Tjassens Keiser <bobby.tjassens.keiser@y-innovate-it.com>, Emma Skovgard <emmaskovgaard@dinoframe.io>, Elijah Swift <elijah.swift@ibm.com>, Frank De Gilio <degilio@us.ibm.com>, Joe Bostian <jbostian@ibm.com>, "Leonard J. Carcaramo Jr" <lcarcaramo@ibm.com>
Maintainer: Emma Skovgard
Maintainer-email: Bobby Tjassens Keiser <bobby.tjassens.keiser@y-innovate-it.com>
License-Expression: Apache-2.0
Project-URL: Homepage, https://github.com/Mainframe-Renewal-Project/sear
Project-URL: Documentation, https://mainframe-renewal-project.github.io/sear-docs/interfaces/python/
Project-URL: Source, https://github.com/Mainframe-Renewal-Project/sear
Project-URL: Issues, https://github.com/Mainframe-Renewal-Project/sear/issues
Project-URL: Release Notes, https://github.com/Mainframe-Renewal-Project/sear/releases
Classifier: Development Status :: 3 - Alpha
Classifier: Intended Audience :: Developers
Classifier: Intended Audience :: System Administrators
Classifier: Operating System :: POSIX :: Other
Classifier: Programming Language :: Assembly
Classifier: Programming Language :: C
Classifier: Programming Language :: C++
Classifier: Programming Language :: Python
Classifier: Programming Language :: Python :: 3
Classifier: Programming Language :: Python :: 3.12
Classifier: Programming Language :: Python :: 3.13
Classifier: Programming Language :: Python :: 3.14
Classifier: Programming Language :: Python :: 3 :: Only
Classifier: Programming Language :: Python :: Implementation :: CPython
Classifier: Programming Language :: Python :: Implementation :: PyPy
Classifier: Topic :: Security
Classifier: Topic :: System :: Hardware :: Mainframes
Classifier: Topic :: System :: Systems Administration
Requires-Python: >=3.12
License-File: LICENSE
License-File: NOTICES
Provides-Extra: dev
Requires-Dist: pytest>=8.4.2; extra == "dev"
Requires-Dist: pytest-md>=0.2.0; extra == "dev"
Dynamic: license-file
